<?xml version="1.0" encoding="UTF-8"?>
<objects serializationModel="Studio.02.02.00">
	<object class="AudioFile" id="{8a7464c2-f5fe-4870-bca4-7766e6b84c9e}">
		<property name="assetPath">
			<value>activate device sound.wav</value>
		</property>
		<property name="isStreaming">
			<value>true</value>
		</property>
		<property name="frequencyInKHz">
			<value>48</value>
		</property>
		<property name="channelCount">
			<value>2</value>
		</property>
		<property name="length">
			<value>15.273479166666666</value>
		</property>
		<relationship name="masterAssetFolder">
			<destination>{9b10ecf2-27d4-441c-a448-3cf8b02d7d16}</destination>
		</relationship>
	</object>
</objects>
